_tkinter.cpython-312.so
libX11.so
libXau.so
libXdmcp.so
libXext.so
libXft.so
libXrender.so
libXss.so
libbrotlicommon.so
libbrotlidec.so
libfontconfig.so
libfreetype.so
libpng16.so
libtcl8.6.so
libtk8.6.so
libxcb.so
setup.py
turtle.py
etc/fonts/fonts.conf
etc/fonts/conf.d/10-hinting-slight.conf
etc/fonts/conf.d/10-scale-bitmap-fonts.conf
etc/fonts/conf.d/10-sub-pixel-none.conf
etc/fonts/conf.d/10-yes-antialias.conf
etc/fonts/conf.d/11-lcdfilter-default.conf
etc/fonts/conf.d/20-unhint-small-dejavu-sans-mono.conf
etc/fonts/conf.d/20-unhint-small-dejavu-sans.conf
etc/fonts/conf.d/20-unhint-small-dejavu-serif.conf
etc/fonts/conf.d/20-unhint-small-vera.conf
etc/fonts/conf.d/30-metric-aliases.conf
etc/fonts/conf.d/40-nonlatin.conf
etc/fonts/conf.d/45-generic.conf
etc/fonts/conf.d/45-latin.conf
etc/fonts/conf.d/48-spacing.conf
etc/fonts/conf.d/49-sansserif.conf
etc/fonts/conf.d/50-user.conf
etc/fonts/conf.d/51-local.conf
etc/fonts/conf.d/57-dejavu-sans-mono.conf
etc/fonts/conf.d/57-dejavu-sans.conf
etc/fonts/conf.d/57-dejavu-serif.conf
etc/fonts/conf.d/60-generic.conf
etc/fonts/conf.d/60-latin.conf
etc/fonts/conf.d/65-fonts-persian.conf
etc/fonts/conf.d/65-nonlatin.conf
etc/fonts/conf.d/69-unifont.conf
etc/fonts/conf.d/80-delicious.conf
etc/fonts/conf.d/90-synthetic.conf
etc/fonts/conf.d/README
idlelib/CREDITS.txt
idlelib/ChangeLog
idlelib/HISTORY.txt
idlelib/NEWS2x.txt
idlelib/News3.txt
idlelib/README.txt
idlelib/TODO.txt
idlelib/__init__.py
idlelib/__main__.py
idlelib/autocomplete.py
idlelib/autocomplete_w.py
idlelib/autoexpand.py
idlelib/browser.py
idlelib/calltip.py
idlelib/calltip_w.py
idlelib/codecontext.py
idlelib/colorizer.py
idlelib/config-extensions.def
idlelib/config-highlight.def
idlelib/config-keys.def
idlelib/config-main.def
idlelib/config.py
idlelib/config_key.py
idlelib/configdialog.py
idlelib/debugger.py
idlelib/debugger_r.py
idlelib/debugobj.py
idlelib/debugobj_r.py
idlelib/delegator.py
idlelib/dynoption.py
idlelib/editor.py
idlelib/extend.txt
tkinter_qpython.egg-info/PKG-INFO
tkinter_qpython.egg-info/SOURCES.txt
tkinter_qpython.egg-info/dependency_links.txt
tkinter_qpython.egg-info/top_level.txt